hatch_vcs/__about__.py
hatch_vcs/__init__.py
hatch_vcs/build_hook.py
hatch_vcs/hooks.py
hatch_vcs/metadata_hook.py
hatch_vcs/vcs_utils.py
hatch_vcs/version_source.py
hatch_vcs-0.3.0.dist-info/METADATA
hatch_vcs-0.3.0.dist-info/WHEEL
hatch_vcs-0.3.0.dist-info/entry_points.txt
hatch_vcs-0.3.0.dist-info/licenses/LICENSE.txt
hatch_vcs-0.3.0.dist-info/RECORD
