Metadata-Version: 2.1
Name: hatch-vcs
Version: 0.3.0
Summary: Hatch plugin for versioning with your preferred VCS
Project-URL: Funding, https://github.com/sponsors/ofek
Project-URL: History, https://github.com/ofek/hatch-vcs/blob/master/HISTORY.md
Project-URL: Issues, https://github.com/ofek/hatch-vcs/issues
Project-URL: Source, https://github.com/ofek/hatch-vcs
Author-email: Ofek Lev <oss@ofek.dev>
License: MIT
License-File: LICENSE.txt
Keywords: git,hatch,mercurial,plugin,scm,vcs,version
Classifier: Development Status :: 4 - Beta
Classifier: Programming Language :: Python
Classifier: Programming Language :: Python :: 3.7
Classifier: Programming Language :: Python :: 3.8
Classifier: Programming Language :: Python :: 3.9
Classifier: Programming Language :: Python :: 3.10
Classifier: Programming Language :: Python :: 3.11
Classifier: Programming Language :: Python :: Implementation :: CPython
Classifier: Programming Language :: Python :: Implementation :: PyPy
Requires-Python: >=3.7
Requires-Dist: hatchling>=1.1.0
Requires-Dist: setuptools-scm>=6.4.0
